{"aliases": ["C94", "コミックマーケット94", "Comiket 94", "Comic Market 94"], "dates": "2018.08.10 - 2018.08.12", "sources": [{"source": "Date: https://web.archive.org/web/20250404235221/https://www.comiket.co.jp/info-a/C94/C94distributions.html", "type": ["Reliable", "Official"]}], "media": [{"path": "94_CWC_C94.png", "sources": [{"source": "https://web.archive.org/web/20180805092358/https://www.comiket.co.jp/", "type": ["Reliable", "Official"]}]}, {"path": "94_CWC_C94L.png", "sources": [{"source": "https://web.archive.org/web/20180805092358/https://www.comiket.co.jp/", "type": ["Reliable", "Official"]}]}, {"path": "94_C94CtlgWeb.jpeg", "sources": [{"source": "https://web.archive.org/web/20250404235221/https://www.comiket.co.jp/info-a/C94/C94distributions.html", "type": ["Reliable", "Official"]}], "comments": "表紙：あおいれびん（サークル：万有）"}, {"path": "94_C94KamibukuroL.jpeg", "sources": [{"source": "https://web.archive.org/web/20250404235221/https://www.comiket.co.jp/info-a/C94/C94distributions.html", "type": ["Reliable", "Official"]}], "comments": "イラスト：POKImari(サークル：POKIZM)"}, {"path": "94_C94KamibukuroS.jpeg", "sources": [{"source": "https://web.archive.org/web/20250404235221/https://www.comiket.co.jp/info-a/C94/C94distributions.html", "type": ["Reliable", "Official"]}], "comments": "イラスト：にゃごしま（サークル：UNDRESS）"}, {"path": "94_C94kigyouPamf.jpeg", "sources": [{"source": "https://web.archive.org/web/20250404235221/https://www.comiket.co.jp/info-a/C94/C94distributions.html", "type": ["Reliable", "Official"]}], "comments": "表紙：ぴこぴこぐらむ（サークル：プラチナきのこ)"}, {"path": "94_C94CtlgRomWeb.jpeg", "sources": [{"source": "https://web.archive.org/web/20250404235221/https://www.comiket.co.jp/info-a/C94/C94distributions.html", "type": ["Reliable", "Official"]}], "comments": "表紙：あおいれびん（サークル：万有）"}, {"path": "94_C94Moushikomisho.jpeg", "sources": [{"source": "https://web.archive.org/web/20250114175314/https://www.comiket.co.jp/info-a/C93/C93distributions.html", "type": ["Reliable", "Official"]}], "comments": "イラスト：わに（サークル：クロコダイルティアーズ）"}, {"path": "http://web.archive.org/web/20180805092452/https://www2.comiket.co.jp/info-a/C94/C94CtlgNotes.pdf", "sources": [{"source": "http://web.archive.org/web/20180805092452/https://www2.comiket.co.jp/info-a/C94/C94CtlgNotes.pdf", "type": ["Reliable", "Official"]}]}]}